retry/__init__.py
retry/api.py
retry/compat.py
py_retry-0.0.5.dist-info/LICENSE
py_retry-0.0.5.dist-info/WHEEL
py_retry-0.0.5.dist-info/METADATA
py_retry-0.0.5.dist-info/RECORD
